decentriq_dcr_compiler-0.19.10.dist-info/METADATA
decentriq_dcr_compiler-0.19.10.dist-info/WHEEL
decentriq_dcr_compiler/__init__.py
decentriq_dcr_compiler/_ddc_py.cp39-win_amd64.pyd
decentriq_dcr_compiler/_schemas/__init__.py
decentriq_dcr_compiler/_schemas/ab_media_dcr.py
decentriq_dcr_compiler/_schemas/ab_media_dcr_latest.py
decentriq_dcr_compiler/_schemas/ab_media_request.py
decentriq_dcr_compiler/_schemas/ab_media_response.py
decentriq_dcr_compiler/_schemas/audience.py
decentriq_dcr_compiler/_schemas/audience_view.py
decentriq_dcr_compiler/_schemas/audit_log_line.py
decentriq_dcr_compiler/_schemas/create_ab_media_dcr.py
decentriq_dcr_compiler/_schemas/create_data_lab.py
decentriq_dcr_compiler/_schemas/create_data_room.py
decentriq_dcr_compiler/_schemas/create_media_dcr.py
decentriq_dcr_compiler/_schemas/data_lab.py
decentriq_dcr_compiler/_schemas/data_room.py
decentriq_dcr_compiler/_schemas/data_room_action.py
decentriq_dcr_compiler/_schemas/data_room_action_response.py
decentriq_dcr_compiler/_schemas/data_room_compute_action.py
decentriq_dcr_compiler/_schemas/data_science_commit.py
decentriq_dcr_compiler/_schemas/data_science_data_room.py
decentriq_dcr_compiler/_schemas/get_parameter_payloads.py
decentriq_dcr_compiler/_schemas/high_level_dcr.py
decentriq_dcr_compiler/_schemas/media_dcr_action.py
decentriq_dcr_compiler/_schemas/requirement_list.py
decentriq_dcr_compiler/_schemas/secret_store_entry_state.py
decentriq_dcr_compiler/_types/__init__.py
decentriq_dcr_compiler/_types/ab_media_dcr.py
decentriq_dcr_compiler/_types/ab_media_dcr_latest.py
decentriq_dcr_compiler/_types/ab_media_request.py
decentriq_dcr_compiler/_types/ab_media_response.py
decentriq_dcr_compiler/_types/audience.py
decentriq_dcr_compiler/_types/audience_view.py
decentriq_dcr_compiler/_types/audit_log_line.py
decentriq_dcr_compiler/_types/create_ab_media_dcr.py
decentriq_dcr_compiler/_types/create_data_lab.py
decentriq_dcr_compiler/_types/create_data_room.py
decentriq_dcr_compiler/_types/create_media_dcr.py
decentriq_dcr_compiler/_types/data_lab.py
decentriq_dcr_compiler-0.19.10.dist-info/RECORD
