Metadata-Version: 2.4
Name: decentriq_dcr_compiler
Version: 0.19.10
Classifier: Programming Language :: Rust
Classifier: Programming Language :: Python :: Implementation :: CPython
Classifier: Programming Language :: Python :: Implementation :: PyPy
Requires-Dist: pydantic==2.*
Requires-Python: >=3.8
